spectrae/__init__.py
spectrae/dataset.py
spectrae/independent_set_algo.py
spectrae/spectra.py
spectrae/utils.py
spectrae-1.0.3.dist-info/LICENSE
spectrae-1.0.3.dist-info/METADATA
spectrae-1.0.3.dist-info/WHEEL
spectrae-1.0.3.dist-info/top_level.txt
spectrae-1.0.3.dist-info/RECORD
