Metadata-Version: 2.1
Name: spectrae
Version: 1.0.3
Summary: SPECTRA: The spectral framework for model evaluation
Home-page: https://github.com/mims-harvard/SPECTRA/
Author: Yasha Ektefaie
Author-email: yasha_ektefaie@g.harvard.edu
License: MIT License
Classifier: Programming Language :: Python :: 3
Classifier: License :: OSI Approved :: MIT License
Classifier: Operating System :: OS Independent
Classifier: Intended Audience :: Science/Research
License-File: LICENSE
Requires-Dist: networkx
Requires-Dist: numpy
Requires-Dist: torch
Requires-Dist: scikit-learn
Requires-Dist: pandas
Requires-Dist: tqdm
